metadata_driver_elasticsearch/__init__.py
metadata_driver_elasticsearch/indexes.py
metadata_driver_elasticsearch/instance.py
metadata_driver_elasticsearch/mapping.py
metadata_driver_elasticsearch/plugin.py
metadata_driver_elasticsearch/utils.py
nevermined_metadata_driver_elasticsearch-0.1.6.dist-info/LICENSE
nevermined_metadata_driver_elasticsearch-0.1.6.dist-info/METADATA
nevermined_metadata_driver_elasticsearch-0.1.6.dist-info/WHEEL
nevermined_metadata_driver_elasticsearch-0.1.6.dist-info/top_level.txt
nevermined_metadata_driver_elasticsearch-0.1.6.dist-info/RECORD
