Metadata-Version: 2.1
Name: nevermined-metadata-driver-elasticsearch
Version: 0.1.6
Summary: 🐳 Metadata ElasticSearch Driver (Python).
Home-page: https://github.com/nevermined-io/metadata-driver-elasticsearch
Author: nevermined-io
Author-email: root@nevermined.io
License: Apache Software License 2.0
Keywords: nevermined-metadata-driver-elasticsearch
Platform: UNKNOWN
Classifier: Development Status :: 2 - Pre-Alpha
Classifier: Intended Audience :: Developers
Classifier: License :: OSI Approved :: Apache Software License
Classifier: Natural Language :: English
Classifier: Programming Language :: Python :: 3.4
Classifier: Programming Language :: Python :: 3.5
Classifier: Programming Language :: Python :: 3.6
License-File: LICENSE
Requires-Dist: nevermined-metadata-driver-interface
Requires-Dist: elasticsearch (~=7.13.1)
Provides-Extra: dev
Requires-Dist: pytest ; extra == 'dev'
Provides-Extra: test
Requires-Dist: pytest ; extra == 'test'
